x_client/__init__.py
x_client/auth.py
x_client/config.py
x_client/exceptions.py
x_client/factory.py
x_client/models.py
x_client/rate_limit.py
x_client/clients/__init__.py
x_client/clients/rate_limited_client.py
x_client/clients/rest_client.py
x_client/clients/tweepy_client.py
x_client/integrations/__init__.py
x_client/integrations/mcp_adapter.py
x_client/integrations/mcp_server.py
x_client/integrations/schema.py
x_client/services/__init__.py
x_client/services/media_service.py
x_client/services/post_service.py
x_client/utils/__init__.py
x_client/utils/text.py
pyx_mcp-0.1.4.dist-info/METADATA
pyx_mcp-0.1.4.dist-info/WHEEL
pyx_mcp-0.1.4.dist-info/entry_points.txt
pyx_mcp-0.1.4.dist-info/top_level.txt
pyx_mcp-0.1.4.dist-info/RECORD
