Metadata-Version: 2.4
Name: pyx-mcp
Version: 0.1.4
Summary: X (Twitter) API client library with tweepy and pydantic
Requires-Python: >=3.11
Requires-Dist: tweepy>=4.16.0
Requires-Dist: pydantic>=2.8.0
Requires-Dist: mcp>=1.17.0
